fastconf/__init__.py
fastconf/fastconf.py
fastconf-1.0.0.dist-info/LICENSE
fastconf-1.0.0.dist-info/METADATA
fastconf-1.0.0.dist-info/WHEEL
fastconf-1.0.0.dist-info/top_level.txt
fastconf-1.0.0.dist-info/RECORD
