Metadata-Version: 2.1
Name: fastconf
Version: 1.0.0
Summary: A simple config lib
Home-page: https://github.com/arwichok/fastconf
Author: Arwichok
Author-email: arwichok@gmail.com
License: MIT
Keywords: config
Platform: UNKNOWN
Requires-Dist: pyyaml
